ssv2py/__init__.py
ssv2py/main.py
ssv2py-0.3.0.dist-info/LICENSE
ssv2py-0.3.0.dist-info/METADATA
ssv2py-0.3.0.dist-info/WHEEL
ssv2py-0.3.0.dist-info/RECORD
