Metadata-Version: 2.3
Name: ssv2py
Version: 0.3.0
Summary: A Python wrapper for the SSV2 API
License: GPL-3.0-only
Keywords: game,minecraft,serverseeker,serverseekerv2
Author: Nucceteere
Author-email: ruzgar@nucceteere.xyz
Requires-Python: >=3.9
Classifier: Development Status :: 4 - Beta
Classifier: Intended Audience :: Developers
Classifier: License :: OSI Approved :: GNU General Public License v3 (GPLv3)
Classifier: Programming Language :: Python :: 3
Classifier: Programming Language :: Python :: 3.9
Classifier: Programming Language :: Python :: 3.10
Classifier: Programming Language :: Python :: 3.11
Classifier: Programming Language :: Python :: 3.12
Classifier: Programming Language :: Python :: 3.13
Classifier: Topic :: Games/Entertainment
Classifier: Topic :: Internet
Classifier: Topic :: Software Development :: Libraries :: Python Modules
Classifier: Topic :: Utilities
Requires-Dist: requests (>=2.32.3,<3.0.0)
Project-URL: Bug Tracker, https://git.funtimes909.xyz/ServerSeekerV2/ssv2py/issues
Project-URL: Contribute, https://git.funtimes909.xyz/ServerSeekerV2/ssv2py/pulls
Project-URL: Documentation, https://git.funtimes909.xyz/ServerSeekerV2/ssv2py/wiki/
Project-URL: Homepage, https://git.funtimes909.xyz/ServerSeekerV2/ssv2py/src/branch/main/README.md
Project-URL: Repository, https://git.funtimes909.xyz/ServerSeekerV2/ssv2py
